{
  "project_info": {
    "project_number": "754603214122",
    "project_id": "nmedia-55929",
    "storage_bucket": "nmedia-55929.appspot.com"
  },
  "client": [
    {
      "client_info": {
        "mobilesdk_app_id": "1:754603214122:android:9a239088327117be7a0a53",
        "android_client_info": {
          "package_name": "ru.netology.nmedia"
        }
      },
      "oauth_client": [
        {
          "client_id": "754603214122-c6a18kojt8j5ssjsepq5tphvuhvsqtov.apps.googleusercontent.com",
          "client_type": 3
        }
      ],
      "api_key": [
        {
          "current_key": "AIzaSyAPwK-FmG0toh_fyawBPi0QEgq0lZnwsKs"
        }
      ],
      "services": {
        "appinvite_service": {
          "other_platform_oauth_client": [
            {
              "client_id": "754603214122-c6a18kojt8j5ssjsepq5tphvuhvsqtov.apps.googleusercontent.com",
              "client_type": 3
            }
          ]
        }
      }
    }
  ],
  "configuration_version": "1"
}